sphinxcontrib_giscus/__init__.py
sphinxcontrib_giscus/_config.py
sphinxcontrib_giscus/_constant.py
sphinxcontrib_giscus/_giscus.py
sphinxcontrib_giscus/py.typed
sphinxcontrib_giscus-0.0.4.dist-info/METADATA
sphinxcontrib_giscus-0.0.4.dist-info/WHEEL
sphinxcontrib_giscus-0.0.4.dist-info/RECORD
