Metadata-Version: 2.4
Name: sphinxcontrib-giscus
Version: 0.0.4
Summary: A sphinx extension that integrate Giscus to your sphinx doc
Project-URL: homepage, https://github.com/un4gt/sphinxcontrib-giscus
Author-email: un4gt <mt3085570450@outlook.com>
Requires-Python: >=3.8
Requires-Dist: sphinx>=7.1.2
